mlbi_svif-0.0.4.dist-info/licenses/LICENSE
svif/__init__.py
svif/gen_ai.py
svif/plot_function_box.py
svif/plot_function_ccidot.py
svif/plot_function_cnv_heatmap.py
svif/plot_function_deg.py
svif/plot_function_gsea.py
svif/plot_function_marker.py
svif/plot_function_stackedbar.py
svif/plot_function_umap.py
svif/plot_function_violin.py
svif/tool_map.py
mlbi_svif-0.0.4.dist-info/METADATA
mlbi_svif-0.0.4.dist-info/WHEEL
mlbi_svif-0.0.4.dist-info/entry_points.txt
mlbi_svif-0.0.4.dist-info/top_level.txt
mlbi_svif-0.0.4.dist-info/RECORD
