Metadata-Version: 2.4
Name: mlbi-svif
Version: 0.0.4
Summary: MLBI Lab SVIF
Author-email: Seokhyun Yoon <syoon@dku.edu>
License-Expression: MIT
Project-URL: Homepage, https://github.com/combio-dku
Keywords: bioinformatics
Classifier: Programming Language :: Python
Classifier: Programming Language :: Python :: 3
License-File: LICENSE
Provides-Extra: dev
Requires-Dist: numpy; extra == "dev"
Requires-Dist: pandas; extra == "dev"
Requires-Dist: scipy; extra == "dev"
Requires-Dist: scikit-learn; extra == "dev"
Requires-Dist: scikit-network; extra == "dev"
Requires-Dist: scanpy; extra == "dev"
Requires-Dist: scoda-viz; extra == "dev"
Dynamic: license-file
